nimbus_setup/__init__.py
nimbus_setup/utils.py
nimbus_setup-3.0.2.dist-info/LICENSE.md
nimbus_setup-3.0.2.dist-info/METADATA
nimbus_setup-3.0.2.dist-info/WHEEL
nimbus_setup-3.0.2.dist-info/top_level.txt
nimbus_setup-3.0.2.dist-info/RECORD
